speechtotext/__init__.py
speechtotext/__version__.py
speechtotext/datasets.py
speechtotext/functions.py
speechtotext/metric/__init__.py
speechtotext/metric/customMetrics.py
speechtotext/metric/metrics.py
speechtotext_python-0.3.15.dist-info/LICENSE
speechtotext_python-0.3.15.dist-info/METADATA
speechtotext_python-0.3.15.dist-info/WHEEL
speechtotext_python-0.3.15.dist-info/top_level.txt
speechtotext_python-0.3.15.dist-info/RECORD
